entropy_invariant/__init__.py
entropy_invariant/_constants.py
entropy_invariant/_types.py
entropy_invariant/advanced.py
entropy_invariant/entropy.py
entropy_invariant/mutual_information.py
entropy_invariant/optimized.py
entropy_invariant/pid.py
entropy_invariant/helpers/__init__.py
entropy_invariant/helpers/computation.py
entropy_invariant/helpers/data.py
entropy_invariant/helpers/utility.py
entropy_invariant-1.1.0.dist-info/METADATA
entropy_invariant-1.1.0.dist-info/WHEEL
entropy_invariant-1.1.0.dist-info/top_level.txt
entropy_invariant-1.1.0.dist-info/RECORD
